collective.recipe.omelette-1.1.1-py3.12-nspkg.pth
collective/recipe/omelette/__init__.py
collective/recipe/omelette/utils.py
collective/recipe/omelette/tests/__init__.py
collective/recipe/omelette/tests/omelette.txt
collective/recipe/omelette/tests/test_docs.py
collective/recipe/omelette/tests/Products/Product1/__init__.py
collective/recipe/omelette/tests/Products/Product1/in_Product1.txt
collective/recipe/omelette/tests/omelettetests.egg1/setup.py
collective/recipe/omelette/tests/omelettetests.egg1/omelettetests/__init__.py
collective/recipe/omelette/tests/omelettetests.egg1/omelettetests/ingredient.py
collective/recipe/omelette/tests/omelettetests.egg1/omelettetests/chicken/__init__.py
collective/recipe/omelette/tests/omelettetests.egg1/omelettetests/chicken/who.py
collective/recipe/omelette/tests/omelettetests.egg1/omelettetests/egg1/__init__.py
collective/recipe/omelette/tests/omelettetests.egg1/omelettetests/egg1/in_egg1.txt
collective/recipe/omelette/tests/package/__init__.py
collective/recipe/omelette/tests/package/Products/__init__.py
collective/recipe/omelette/tests/package/Products/Product1/__init__.py
collective/recipe/omelette/tests/package/Products/Product1/in_packaged_Product1.txt
collective/recipe/omelette/tests/package/Products/Product2/__init__.py
collective/recipe/omelette/tests/package/Products/Product2/in_packaged_Product2.txt
collective/recipe/omelette/tests/package/subpackage/__init__.py
collective/recipe/omelette/tests/package/subpackage/in_subpackage.txt
collective.recipe.omelette-1.1.1.dist-info/METADATA
collective.recipe.omelette-1.1.1.dist-info/WHEEL
collective.recipe.omelette-1.1.1.dist-info/entry_points.txt
collective.recipe.omelette-1.1.1.dist-info/namespace_packages.txt
collective.recipe.omelette-1.1.1.dist-info/top_level.txt
collective.recipe.omelette-1.1.1.dist-info/RECORD
