Metadata-Version: 2.1
Name: collective.recipe.omelette
Version: 1.1.1
Summary: Creates a unified directory structure of installed packages, symlinking to the actual contents, in order to ease navigation.
Home-page: https://github.com/collective/collective.recipe.omelette
Author: David Glick, Groundwire
Author-email: davidglick@groundwire.org
License: GPL
Keywords: buildout eggs namespace
Classifier: Development Status :: 5 - Production/Stable
Classifier: Framework :: Buildout
Classifier: Intended Audience :: Developers
Classifier: Topic :: Software Development :: Build Tools
Classifier: Topic :: Software Development :: Libraries :: Python Modules
Classifier: License :: OSI Approved :: GNU General Public License (GPL)
Classifier: Programming Language :: Python :: 2.7
Classifier: Programming Language :: Python :: 3.6
Classifier: Programming Language :: Python :: 3.7
Classifier: Programming Language :: Python :: 3.8
Classifier: Programming Language :: Python :: 3.9
Classifier: Programming Language :: Python :: 3.10
Requires-Dist: setuptools
Requires-Dist: zc.buildout
Requires-Dist: zc.recipe.egg
Provides-Extra: tests
Requires-Dist: zope.testing; extra == "tests"
Requires-Dist: zc.buildout[test]; extra == "tests"
Requires-Dist: zc.recipe.egg; extra == "tests"
Requires-Dist: pytest; extra == "tests"
